apstools/__init__.py
apstools/_version.py
apstools/callbacks/__init__.py
apstools/callbacks/callback_base.py
apstools/callbacks/doc_collector.py
apstools/callbacks/nexus_writer.py
apstools/callbacks/scan_signal_statistics.py
apstools/callbacks/spec_file_writer.py
apstools/callbacks/tests/__init__.py
apstools/callbacks/tests/conftest.py
apstools/callbacks/tests/test_440_specwriter.py
apstools/callbacks/tests/test_filewriter.py
apstools/callbacks/tests/test_i1123_specwriter.py
apstools/callbacks/tests/test_i806_nxwriter.py
apstools/callbacks/tests/test_nxwriter.py
apstools/callbacks/tests/test_specwriter.py
apstools/devices/__init__.py
apstools/devices/acs_motors.py
apstools/devices/aps_bss_user.py
apstools/devices/aps_cycle.py
apstools/devices/aps_cycle_info.yml
apstools/devices/aps_data_management.py
apstools/devices/aps_machine.py
apstools/devices/aps_undulator.py
apstools/devices/area_detector_factory.py
apstools/devices/area_detector_support.py
apstools/devices/avs_filters.py
apstools/devices/axis_tuner.py
apstools/devices/delay.py
apstools/devices/description_mixin.py
apstools/devices/dict_device_support.py
apstools/devices/epics_scan_id_signal.py
apstools/devices/eurotherm_2216e.py
apstools/devices/flyer_motor_scaler.py_i763
apstools/devices/hhl_apertures.py
apstools/devices/hhl_slits.py
apstools/devices/jj_transfocators.py
apstools/devices/kohzu_monochromator.py
apstools/devices/labjack.py
apstools/devices/lakeshore_controllers.py
apstools/devices/linkam_controllers.py
apstools/devices/measComp_tc32_support.py
apstools/devices/measComp_usb_ctr_support.py
apstools/devices/mixin_base.py
apstools/devices/motor_factory.py
apstools/devices/motor_mixins.py
apstools/devices/positioner_soft_done.py
apstools/devices/preamp_base.py
apstools/devices/pss_shutter.db
apstools/devices/pss_shutter.ui
apstools/devices/ptc10_controller.py
apstools/devices/scaler_support.py
apstools/devices/shutters.py
apstools/devices/simulated_controllers.py
apstools-1.7.9.dist-info/licenses/LICENSE.txt
apstools-1.7.9.dist-info/METADATA
apstools-1.7.9.dist-info/WHEEL
apstools-1.7.9.dist-info/entry_points.txt
apstools-1.7.9.dist-info/top_level.txt
apstools-1.7.9.dist-info/RECORD
